{"trial_id": "0012", "hyperparameters": {"space": [{"class_name": "Int", "config": {"name": "num_conv_layers", "default": null, "conditions": [], "min_value": 1, "max_value": 4, "step": 1, "sampling": "linear"}}, {"class_name": "Int", "config": {"name": "conv_kernel_size_0_height", "default": null, "conditions": [], "min_value": 2, "max_value": 6, "step": 1, "sampling": "linear"}}, {"class_name": "Int", "config": {"name": "conv_kernel_size_0_width", "default": null, "conditions": [], "min_value": 2, "max_value": 6, "step": 1, "sampling": "linear"}}, {"class_name": "Choice", "config": {"name": "conv_strides_0", "default": 1, "conditions": [], "values": [1, 2], "ordered": true}}, {"class_name": "Choice", "config": {"name": "conv_filters_0", "default": 32, "conditions": [], "values": [32, 64, 128, 156], "ordered": true}}, {"class_name": "Int", "config": {"name": "maxpool_size_0_height", "default": null, "conditions": [], "min_value": 1, "max_value": 4, "step": 1, "sampling": "linear"}}, {"class_name": "Int", "config": {"name": "maxpool_size_0_width", "default": null, "conditions": [], "min_value": 1, "max_value": 4, "step": 1, "sampling": "linear"}}, {"class_name": "Int", "config": {"name": "num_dense_layers", "default": null, "conditions": [], "min_value": 1, "max_value": 6, "step": 1, "sampling": "linear"}}, {"class_name": "Int", "config": {"name": "dense_units_0", "default": null, "conditions": [], "min_value": 32, "max_value": 128, "step": 32, "sampling": "linear"}}, {"class_name": "Choice", "config": {"name": "l2_reg_dense_0", "default": 1e-05, "conditions": [], "values": [1e-05, 0.0001, 0.005, 0.01], "ordered": true}}, {"class_name": "Float", "config": {"name": "dropout_0", "default": 0.1, "conditions": [], "min_value": 0.1, "max_value": 0.4, "step": 0.1, "sampling": "linear"}}, {"class_name": "Choice", "config": {"name": "learning_rate", "default": 0.1, "conditions": [], "values": [0.1, 0.001, 0.0001], "ordered": true}}, {"class_name": "Int", "config": {"name": "conv_kernel_size_1_height", "default": null, "conditions": [], "min_value": 2, "max_value": 6, "step": 1, "sampling": "linear"}}, {"class_name": "Int", "config": {"name": "conv_kernel_size_1_width", "default": null, "conditions": [], "min_value": 2, "max_value": 6, "step": 1, "sampling": "linear"}}, {"class_name": "Choice", "config": {"name": "conv_strides_1", "default": 1, "conditions": [], "values": [1, 2], "ordered": true}}, {"class_name": "Choice", "config": {"name": "conv_filters_1", "default": 32, "conditions": [], "values": [32, 64, 128, 156], "ordered": true}}, {"class_name": "Int", "config": {"name": "maxpool_size_1_height", "default": null, "conditions": [], "min_value": 1, "max_value": 4, "step": 1, "sampling": "linear"}}, {"class_name": "Int", "config": {"name": "maxpool_size_1_width", "default": null, "conditions": [], "min_value": 1, "max_value": 4, "step": 1, "sampling": "linear"}}, {"class_name": "Int", "config": {"name": "conv_kernel_size_2_height", "default": null, "conditions": [], "min_value": 2, "max_value": 6, "step": 1, "sampling": "linear"}}, {"class_name": "Int", "config": {"name": "conv_kernel_size_2_width", "default": null, "conditions": [], "min_value": 2, "max_value": 6, "step": 1, "sampling": "linear"}}, {"class_name": "Choice", "config": {"name": "conv_strides_2", "default": 1, "conditions": [], "values": [1, 2], "ordered": true}}, {"class_name": "Choice", "config": {"name": "conv_filters_2", "default": 32, "conditions": [], "values": [32, 64, 128, 156], "ordered": true}}, {"class_name": "Int", "config": {"name": "maxpool_size_2_height", "default": null, "conditions": [], "min_value": 1, "max_value": 4, "step": 1, "sampling": "linear"}}, {"class_name": "Int", "config": {"name": "maxpool_size_2_width", "default": null, "conditions": [], "min_value": 1, "max_value": 4, "step": 1, "sampling": "linear"}}, {"class_name": "Int", "config": {"name": "dense_units_1", "default": null, "conditions": [], "min_value": 32, "max_value": 128, "step": 32, "sampling": "linear"}}, {"class_name": "Choice", "config": {"name": "l2_reg_dense_1", "default": 1e-05, "conditions": [], "values": [1e-05, 0.0001, 0.005, 0.01], "ordered": true}}, {"class_name": "Float", "config": {"name": "dropout_1", "default": 0.1, "conditions": [], "min_value": 0.1, "max_value": 0.4, "step": 0.1, "sampling": "linear"}}, {"class_name": "Int", "config": {"name": "dense_units_2", "default": null, "conditions": [], "min_value": 32, "max_value": 128, "step": 32, "sampling": "linear"}}, {"class_name": "Choice", "config": {"name": "l2_reg_dense_2", "default": 1e-05, "conditions": [], "values": [1e-05, 0.0001, 0.005, 0.01], "ordered": true}}, {"class_name": "Float", "config": {"name": "dropout_2", "default": 0.1, "conditions": [], "min_value": 0.1, "max_value": 0.4, "step": 0.1, "sampling": "linear"}}, {"class_name": "Int", "config": {"name": "dense_units_3", "default": null, "conditions": [], "min_value": 32, "max_value": 128, "step": 32, "sampling": "linear"}}, {"class_name": "Choice", "config": {"name": "l2_reg_dense_3", "default": 1e-05, "conditions": [], "values": [1e-05, 0.0001, 0.005, 0.01], "ordered": true}}, {"class_name": "Float", "config": {"name": "dropout_3", "default": 0.1, "conditions": [], "min_value": 0.1, "max_value": 0.4, "step": 0.1, "sampling": "linear"}}, {"class_name": "Int", "config": {"name": "conv_kernel_size_3_height", "default": null, "conditions": [], "min_value": 2, "max_value": 6, "step": 1, "sampling": "linear"}}, {"class_name": "Int", "config": {"name": "conv_kernel_size_3_width", "default": null, "conditions": [], "min_value": 2, "max_value": 6, "step": 1, "sampling": "linear"}}, {"class_name": "Choice", "config": {"name": "conv_strides_3", "default": 1, "conditions": [], "values": [1, 2], "ordered": true}}, {"class_name": "Choice", "config": {"name": "conv_filters_3", "default": 32, "conditions": [], "values": [32, 64, 128, 156], "ordered": true}}, {"class_name": "Int", "config": {"name": "maxpool_size_3_height", "default": null, "conditions": [], "min_value": 1, "max_value": 4, "step": 1, "sampling": "linear"}}, {"class_name": "Int", "config": {"name": "maxpool_size_3_width", "default": null, "conditions": [], "min_value": 1, "max_value": 4, "step": 1, "sampling": "linear"}}, {"class_name": "Int", "config": {"name": "dense_units_4", "default": null, "conditions": [], "min_value": 32, "max_value": 128, "step": 32, "sampling": "linear"}}, {"class_name": "Choice", "config": {"name": "l2_reg_dense_4", "default": 1e-05, "conditions": [], "values": [1e-05, 0.0001, 0.005, 0.01], "ordered": true}}, {"class_name": "Float", "config": {"name": "dropout_4", "default": 0.1, "conditions": [], "min_value": 0.1, "max_value": 0.4, "step": 0.1, "sampling": "linear"}}, {"class_name": "Int", "config": {"name": "dense_units_5", "default": null, "conditions": [], "min_value": 32, "max_value": 128, "step": 32, "sampling": "linear"}}, {"class_name": "Choice", "config": {"name": "l2_reg_dense_5", "default": 1e-05, "conditions": [], "values": [1e-05, 0.0001, 0.005, 0.01], "ordered": true}}, {"class_name": "Float", "config": {"name": "dropout_5", "default": 0.1, "conditions": [], "min_value": 0.1, "max_value": 0.4, "step": 0.1, "sampling": "linear"}}], "values": {"num_conv_layers": 4, "conv_kernel_size_0_height": 5, "conv_kernel_size_0_width": 6, "conv_strides_0": 1, "conv_filters_0": 32, "maxpool_size_0_height": 2, "maxpool_size_0_width": 4, "num_dense_layers": 2, "dense_units_0": 96, "l2_reg_dense_0": 0.0001, "dropout_0": 0.2, "learning_rate": 0.001, "conv_kernel_size_1_height": 3, "conv_kernel_size_1_width": 5, "conv_strides_1": 2, "conv_filters_1": 64, "maxpool_size_1_height": 3, "maxpool_size_1_width": 4, "conv_kernel_size_2_height": 3, "conv_kernel_size_2_width": 3, "conv_strides_2": 1, "conv_filters_2": 64, "maxpool_size_2_height": 2, "maxpool_size_2_width": 2, "dense_units_1": 32, "l2_reg_dense_1": 0.0001, "dropout_1": 0.30000000000000004, "dense_units_2": 32, "l2_reg_dense_2": 0.01, "dropout_2": 0.1, "dense_units_3": 128, "l2_reg_dense_3": 0.005, "dropout_3": 0.30000000000000004, "conv_kernel_size_3_height": 2, "conv_kernel_size_3_width": 6, "conv_strides_3": 2, "conv_filters_3": 128, "maxpool_size_3_height": 3, "maxpool_size_3_width": 2, "tuner/epochs": 4, "tuner/initial_epoch": 2, "tuner/bracket": 2, "tuner/round": 1, "tuner/trial_id": "0006", "dense_units_4": 128, "l2_reg_dense_4": 0.01, "dropout_4": 0.30000000000000004, "dense_units_5": 96, "l2_reg_dense_5": 1e-05, "dropout_5": 0.1}}, "metrics": {"metrics": {"accuracy": {"direction": "max", "observations": [{"value": [0.4677993953227997], "step": 1}]}, "loss": {"direction": "min", "observations": [{"value": [1.4066791534423828], "step": 1}]}, "val_accuracy": {"direction": "max", "observations": [{"value": [0.48498231172561646], "step": 1}]}, "val_loss": {"direction": "min", "observations": [{"value": [1.3279577493667603], "step": 1}]}}}, "score": 0.48498231172561646, "best_step": 1, "status": "COMPLETED", "message": null}