{"ongoing_trials": {}, "hyperparameters": {"space": [{"class_name": "Choice", "config": {"name": "conv_l2", "default": 0.0001, "conditions": [], "values": [0.0001, 0.001, 0.005], "ordered": true}}, {"class_name": "Choice", "config": {"name": "conv_kernel_size_1", "default": 3, "conditions": [], "values": [3, 4], "ordered": true}}, {"class_name": "Choice", "config": {"name": "conv_filters_1", "default": 32, "conditions": [], "values": [32, 64, 128], "ordered": true}}, {"class_name": "Choice", "config": {"name": "conv_kernel_size_2", "default": 3, "conditions": [], "values": [3, 4], "ordered": true}}, {"class_name": "Choice", "config": {"name": "conv_filters_2_factor", "default": 1, "conditions": [], "values": [1, 2], "ordered": true}}, {"class_name": "Choice", "config": {"name": "conv_kernel_size_3", "default": 3, "conditions": [], "values": [3, 4], "ordered": true}}, {"class_name": "Choice", "config": {"name": "conv_filters_3_factor", "default": 1, "conditions": [], "values": [1, 2], "ordered": true}}, {"class_name": "Boolean", "config": {"name": "use_4_conv", "default": false, "conditions": []}}, {"class_name": "Int", "config": {"name": "dense_units_1", "default": null, "conditions": [], "min_value": 32, "max_value": 128, "step": 32, "sampling": "linear"}}, {"class_name": "Choice", "config": {"name": "l2_dense1", "default": 0.0001, "conditions": [], "values": [0.0001, 0.001, 0.005], "ordered": true}}, {"class_name": "Boolean", "config": {"name": "use_dense_2", "default": false, "conditions": []}}, {"class_name": "Float", "config": {"name": "dropout", "default": 0.0, "conditions": [], "min_value": 0.0, "max_value": 0.4, "step": 0.1, "sampling": "linear"}}, {"class_name": "Choice", "config": {"name": "learning_rate", "default": 0.1, "conditions": [], "values": [0.1, 0.001, 0.0001], "ordered": true}}, {"class_name": "Choice", "config": {"name": "conv_kernel_size_4", "default": 3, "conditions": [], "values": [3, 4], "ordered": true}}, {"class_name": "Choice", "config": {"name": "conv_filters_4_factor", "default": 1, "conditions": [], "values": [1, 2], "ordered": true}}, {"class_name": "Int", "config": {"name": "dense_units_2", "default": null, "conditions": [], "min_value": 32, "max_value": 128, "step": 32, "sampling": "linear"}}, {"class_name": "Choice", "config": {"name": "l2_dense2", "default": 0.0001, "conditions": [], "values": [0.0001, 0.001, 0.005], "ordered": true}}], "values": {"conv_l2": 0.0001, "conv_kernel_size_1": 3, "conv_filters_1": 32, "conv_kernel_size_2": 3, "conv_filters_2_factor": 1, "conv_kernel_size_3": 3, "conv_filters_3_factor": 1, "use_4_conv": false, "dense_units_1": 32, "l2_dense1": 0.0001, "use_dense_2": false, "dropout": 0.0, "learning_rate": 0.1, "conv_kernel_size_4": 3, "conv_filters_4_factor": 1, "dense_units_2": 32, "l2_dense2": 0.0001}}, "start_order": ["0000", "0001", "0002", "0003", "0004", "0005", "0006", "0007", "0008", "0009", "0010", "0011", "0012", "0013", "0014", "0015", "0016", "0017", "0018", "0019", "0020", "0021", "0022", "0023", "0024", "0025", "0026", "0027", "0028", "0029"], "end_order": ["0000", "0001", "0002", "0003", "0004", "0005", "0006", "0007", "0008", "0009", "0010", "0011", "0012", "0013", "0014", "0015", "0016", "0017", "0018", "0019", "0020", "0021", "0022", "0023", "0024", "0025", "0026", "0027", "0028", "0029"], "run_times": {"0000": 1, "0001": 1, "0002": 1, "0003": 1, "0004": 1, "0005": 1, "0006": 1, "0007": 1, "0008": 1, "0009": 1, "0010": 1, "0011": 1, "0012": 1, "0013": 1, "0014": 1, "0015": 1, "0016": 1, "0017": 1, "0018": 1, "0019": 1, "0020": 1, "0021": 1, "0022": 1, "0023": 1, "0024": 1, "0025": 1, "0026": 1, "0027": 1, "0028": 1, "0029": 1}, "retry_queue": [], "seed": 5408, "seed_state": 5774, "tried_so_far": ["eb8633e2691733703943d6b601b55980", "77dc171675b2b15a46b98d02367ea596", "c92acc653291fca4e9e8583583acbd19", "dd3d19cb7bf9903d414d515bb05b21a1", "4ea8ff7b1efc9771cb752e3f562cd0ac", "86fa431ca0674f682ddeca0431f5dc68", "2538177a81a3e13259ad94699e5441c1", "c1a103bc3846df3e79b2f0a8f0e2231f", "3e9a0c1d31534f35d0f488d26bff5050", "cfe07d6c8dd2acdd1804ae077aaf4617", "a9a31527f3815cf647bb6f38d8a3d63e", "44a70f69f10117c862a14719e9a69033", "903f0cfe5057dac6b1ab058c20cf21bc", "ca54657e281a2bebb5f323d18ea8c45f", "bc475b4f4fb92782e56595e330e71c7f", "f4b474ef922b423f571eea87ab18ee0a", "f4390970f628d1e253f6eca058b5d40c", "5a1ad3422f775532a74b89958ca17b36", "b64db89a70160342a501e6b5fc4776a1", "a30426b9a9ec2a4bf1a3baafcfcf7597", "92bdd82610a289ad909e2d6870f24baf", "e48cd571c348f37b835311498a6575ef", "ef12e8042a22843f82f7e561f88341d7", "59215526a8339f4fc2d22519026488bc", "6b6dfaeda1f121c7424e5fc717557280", "48a721b5aa9aa1fa6df9a069fe2c4b9b", "2393ddb83e3c0e2095042deb0e2ef867", "8f75facd1f0fcf1123cd2a7f467de71f", "2b17e6403d96f3da90aa9b4f89eae47d", "11d2815be923852653730c1be0798b53"], "id_to_hash": {"0000": "b64db89a70160342a501e6b5fc4776a1", "0001": "6b6dfaeda1f121c7424e5fc717557280", "0002": "c1a103bc3846df3e79b2f0a8f0e2231f", "0003": "11d2815be923852653730c1be0798b53", "0004": "2b17e6403d96f3da90aa9b4f89eae47d", "0005": "48a721b5aa9aa1fa6df9a069fe2c4b9b", "0006": "a30426b9a9ec2a4bf1a3baafcfcf7597", "0007": "44a70f69f10117c862a14719e9a69033", "0008": "e48cd571c348f37b835311498a6575ef", "0009": "903f0cfe5057dac6b1ab058c20cf21bc", "0010": "bc475b4f4fb92782e56595e330e71c7f", "0011": "8f75facd1f0fcf1123cd2a7f467de71f", "0012": "ef12e8042a22843f82f7e561f88341d7", "0013": "4ea8ff7b1efc9771cb752e3f562cd0ac", "0014": "77dc171675b2b15a46b98d02367ea596", "0015": "cfe07d6c8dd2acdd1804ae077aaf4617", "0016": "f4390970f628d1e253f6eca058b5d40c", "0017": "92bdd82610a289ad909e2d6870f24baf", "0018": "dd3d19cb7bf9903d414d515bb05b21a1", "0019": "2393ddb83e3c0e2095042deb0e2ef867", "0020": "86fa431ca0674f682ddeca0431f5dc68", "0021": "f4b474ef922b423f571eea87ab18ee0a", "0022": "ca54657e281a2bebb5f323d18ea8c45f", "0023": "c92acc653291fca4e9e8583583acbd19", "0024": "5a1ad3422f775532a74b89958ca17b36", "0025": "eb8633e2691733703943d6b601b55980", "0026": "2538177a81a3e13259ad94699e5441c1", "0027": "3e9a0c1d31534f35d0f488d26bff5050", "0028": "59215526a8339f4fc2d22519026488bc", "0029": "a9a31527f3815cf647bb6f38d8a3d63e"}, "display": {"search_start": "2025-02-11T00:13:08.127843", "trial_start": {"0000": "2025-02-11T00:13:08.127843", "0001": "2025-02-11T00:14:46.447261", "0002": "2025-02-11T00:16:40.435384", "0003": "2025-02-11T00:19:02.861874", "0004": "2025-02-11T00:36:07.768903", "0005": "2025-02-11T00:37:11.565918", "0006": "2025-02-11T00:43:39.625871", "0007": "2025-02-11T00:44:52.273632", "0008": "2025-02-11T00:49:11.972327", "0009": "2025-02-11T00:53:29.678572", "0010": "2025-02-11T01:01:09.021433", "0011": "2025-02-11T01:04:31.964037", "0012": "2025-02-11T01:22:46.743681", "0013": "2025-02-11T01:40:50.736362", "0014": "2025-02-11T01:46:49.331562", "0015": "2025-02-11T01:47:51.030459", "0016": "2025-02-11T01:49:54.954931", "0017": "2025-02-11T02:43:38.960332", "0018": "2025-02-11T02:46:35.521198", "0019": "2025-02-11T03:12:40.285760", "0020": "2025-02-11T03:16:22.115581", "0021": "2025-02-11T03:25:17.968577", "0022": "2025-02-11T03:27:58.001121", "0023": "2025-02-11T03:31:51.915796", "0024": "2025-02-11T03:34:01.896899", "0025": "2025-02-11T03:39:28.911239", "0026": "2025-02-11T03:45:20.387980", "0027": "2025-02-11T04:49:52.630920", "0028": "2025-02-11T05:03:28.478560", "0029": "2025-02-11T05:09:26.705076"}, "trial_number": {"0000": 1, "0001": 2, "0002": 3, "0003": 4, "0004": 5, "0005": 6, "0006": 7, "0007": 8, "0008": 9, "0009": 10, "0010": 11, "0011": 12, "0012": 13, "0013": 14, "0014": 15, "0015": 16, "0016": 17, "0017": 18, "0018": 19, "0019": 20, "0020": 21, "0021": 22, "0022": 23, "0023": 24, "0024": 25, "0025": 26, "0026": 27, "0027": 28, "0028": 29, "0029": 30}}, "hyperband_iterations": 1, "max_epochs": 10, "min_epochs": 1, "factor": 3, "brackets": [{"bracket_num": 0, "rounds": [[{"past_id": null, "id": "0026"}, {"past_id": null, "id": "0027"}, {"past_id": null, "id": "0028"}, {"past_id": null, "id": "0029"}]]}], "current_bracket": 0, "current_iteration": 0}